svgout/__init__.py
svgout/cli.py
svgout/manipulator.py
svgout-0.1.0.dist-info/METADATA
svgout-0.1.0.dist-info/WHEEL
svgout-0.1.0.dist-info/entry_points.txt
svgout-0.1.0.dist-info/top_level.txt
svgout-0.1.0.dist-info/RECORD
