Metadata-Version: 2.1
Name: svgout
Version: 0.1.0
Summary: Manipulate SVG elements and export variations
Home-page: http://github.com/meyt/svgout
Author: Mahdi Ghane.g
License: MIT
Keywords: svg
Platform: UNKNOWN
Classifier: Development Status :: 3 - Alpha
Classifier: Intended Audience :: Developers
Classifier: License :: OSI Approved :: MIT License
Classifier: Operating System :: POSIX :: Linux
Classifier: Operating System :: Unix
Classifier: Programming Language :: Python :: 3.8
Classifier: Topic :: Software Development :: Libraries
Requires-Dist: beautifulsoup4 (==4.9.3)
Requires-Dist: cssutils (==1.0.2)
Requires-Dist: lxml (==4.6.2)
Requires-Dist: pyyaml (==5.3.1)
